doc_gen/__init__.py
doc_gen/generate_doc.py
jchord/__init__.py
jchord/chords.py
jchord/convert.py
jchord/core.py
jchord/example.py
jchord/group_notes_to_chords.py
jchord/knowledge.py
jchord/midi.py
jchord/midi_effects.py
jchord/progressions.py
jchord-3.1.1.dist-info/LICENSE.md
jchord-3.1.1.dist-info/METADATA
jchord-3.1.1.dist-info/WHEEL
jchord-3.1.1.dist-info/entry_points.txt
jchord-3.1.1.dist-info/top_level.txt
jchord-3.1.1.dist-info/RECORD
