Metadata-Version: 2.1
Name: jchord
Version: 3.1.1
Summary: Python toolkit for working with chord progressions
Home-page: https://github.com/jonathangjertsen/jchord
Author: Jonathan Reichelt Gjertsen
Author-email: jonath.re@gmail.com
License: MIT
Project-URL: Documentation, https://github.com/jonathangjertsen/jchord
Project-URL: Source, https://github.com/jonathangjertsen/jchord
Platform: UNKNOWN
Classifier: Development Status :: 4 - Beta
Classifier: Intended Audience :: Developers
Classifier: Natural Language :: English
Classifier: License :: OSI Approved :: MIT License
Classifier: Programming Language :: Python
Classifier: Programming Language :: Python :: 3
Classifier: Programming Language :: Python :: 3.7
Classifier: Programming Language :: Python :: 3.8
Classifier: Programming Language :: Python :: Implementation :: CPython
License-File: LICENSE.md
Provides-Extra: midi
Requires-Dist: mido ; extra == 'midi'
Provides-Extra: pdf
Requires-Dist: reportlab ; extra == 'pdf'
Provides-Extra: xlsx
Requires-Dist: openpyxl ; extra == 'xlsx'
